SDTapi/Tools.py
SDTapi/__init__.py
SDTapi/example.py
SDTapi/test.py
SDTapi/upAndDown.py
SDTapi/Scripts/AdjoinParcels.cp38-win_amd64.pyd
SDTapi/Scripts/AutoWriteXML.cp38-win_amd64.pyd
SDTapi/Scripts/Block.cp38-win_amd64.pyd
SDTapi/Scripts/CutByShp.cp38-win_amd64.pyd
SDTapi/Scripts/LandsatLayerStack.cp38-win_amd64.pyd
SDTapi/Scripts/OutJpg.cp38-win_amd64.pyd
SDTapi/Scripts/Raster2Vector.cp38-win_amd64.pyd
SDTapi/Scripts/SVMSupervisedClassification.cp38-win_amd64.pyd
SDTapi/Scripts/SentinelDown.cp38-win_amd64.pyd
SDTapi/Scripts/SentinelToTif.cp38-win_amd64.pyd
SDTapi/Scripts/ShpSmoothness.cp38-win_amd64.pyd
SDTapi/Scripts/ThresholdSeg.cp38-win_amd64.pyd
SDTapi/Scripts/Vector2Raster.cp38-win_amd64.pyd
SDTapi/Scripts/WaterExtract.cp38-win_amd64.pyd
SDTapi/Scripts/ZonalStatistics.cp38-win_amd64.pyd
SDTapi/Scripts/__init__.py
SDTapi/Scripts/cut.cp38-win_amd64.pyd
SDTapi/Scripts/down.cp38-win_amd64.pyd
SDTapi/Scripts/transform.cp38-win_amd64.pyd
SDTapi-0.2.5.dist-info/LICENSE
SDTapi-0.2.5.dist-info/METADATA
SDTapi-0.2.5.dist-info/WHEEL
SDTapi-0.2.5.dist-info/top_level.txt
SDTapi-0.2.5.dist-info/RECORD
