Metadata-Version: 2.1
Name: SDTapi
Version: 0.2.5
Summary: SDT测试产品
Home-page: UNKNOWN
Author: bmd
Author-email: 1790523836@qq.com
License: UNKNOWN
Platform: UNKNOWN
Requires-Python: >=3.8
